mdns_filoxy/__init__.py
mdns_filoxy/_version.py
mdns_filoxy/main.py
mdns_filoxy/utils.py
mdns_filoxy-1.0.5.dist-info/METADATA
mdns_filoxy-1.0.5.dist-info/WHEEL
mdns_filoxy-1.0.5.dist-info/entry_points.txt
mdns_filoxy-1.0.5.dist-info/licenses/LICENSE.txt
mdns_filoxy-1.0.5.dist-info/RECORD
