Metadata-Version: 2.4
Name: mdns-filoxy
Version: 1.0.5
Summary: This is mdns-filoxy, the mDNS filter proxy!
Project-URL: Documentation, https://github.com/lingfish/mdns-filoxy
Project-URL: Issues, https://github.com/lingfish/mdns-filoxy/issues
Project-URL: Source, https://github.com/lingfish/mdns-filoxy
Author-email: Jason Lingohr <jason@lucid.net.au>
License-Expression: MIT
License-File: LICENSE.txt
Classifier: Development Status :: 5 - Production/Stable
Classifier: Programming Language :: Python
Classifier: Programming Language :: Python :: 3.8
Classifier: Programming Language :: Python :: 3.9
Classifier: Programming Language :: Python :: 3.10
Classifier: Programming Language :: Python :: 3.11
Classifier: Programming Language :: Python :: 3.12
Classifier: Programming Language :: Python :: Implementation :: CPython
Classifier: Programming Language :: Python :: Implementation :: PyPy
Requires-Python: >=3.8
Requires-Dist: click
Requires-Dist: loguru
Requires-Dist: zeroconf
